{
  "name": "初音ミク",
  "author": "robflop",
  "desc": "Misskeyもみくみくにしてあげる",
  "base": "dark",
  "props": {
    "accent": "#e12885",
    "accentDarken": ":darken<10<@accent",
    "accentLighten": ":lighten<10<@accent",
    "accentShadow": ":alpha<0.3<@accent",
    "focus": ":alpha<0.3<@accent",
    "bg": "#373b3e",
    "fg": "#86cecb",
    "fgHighlighted": "#d0d8de",
    "html": "#373b3e",
    "indicator": "@accent",
    "panel": "#111213",
    "shadow": "rgba(0, 0, 0, 0.1)",
    "header": "rgba(20, 20, 20, 0.75)",
    "pageBg": "#0d0d0d",
    "navBg": "@panel",
    "navFg": "@fg",
    "navHoverFg": "#fafbfc",
    "navActive": "@accent",
    "navIndicator": "@accent",
    "link": "#44a4c1",
    "hashtag": "#ff9156",
    "mention": "@accent",
    "mentionMe": "@accent",
    "renote": "@accentLighten",
    "modalBg": "rgba(0, 0, 0, 0.5)",
    "divider": "rgba(255, 255, 255, 0.1)",
    "scrollbarHandle": "rgba(255, 255, 255, 0.2)",
    "scrollbarHandleHover": "rgba(255, 255, 255, 0.4)",
    "dateLabelFg": "#ffffff",
    "infoBg": "#253142",
    "infoFg": "#ffffff",
    "infoWarnBg": "#42321c",
    "infoWarnFg": "#ffbd3e",
    "cwBg": "#a1adba",
    "cwFg": "#393f4f",
    "cwHoverBg": ":lighten<10<@cwBg",
    "toastBg": "rgba(0, 0, 0, 0.5)",
    "toastFg": "#c7d1d8",
    "buttonBg": "rgba(255, 255, 255, 0.05)",
    "buttonHoverBg": "rgba(255, 255, 255, 0.1)",
    "inputBorder": "#959da2",
    "listItemHoverBg": "rgba(255, 255, 255, 0.03)",
    "driveFolderBg": ":darken<30<#667c90",
    "wallpaperOverlay": "rgba(0, 0, 0, 0.5)",
    "badge": "#31b1ce",
    "messageBg": "#0d0d0d",
    "bonzsgfz": "rgba(0, 0, 0, 0)",
    "pcncwizz": "#0c0d0e",
    "yrnqrguo": "rgba(255, 255, 255, 0.05)",
    "nwjktjjq": "rgba(255, 255, 255, 0.1)",
    "geavgsxy": "rgba(255, 255, 255, 0.05)",
    "nhzhphzx": "rgba(255, 255, 255, 0.15)",
    "bwqtlupy": "rgba(255, 255, 255, 0.05)",
    "jkhztclx": "#e43e92",
    "zbqjwygh": "#d21d78",
    "xxubwiul": "rgba(225, 40, 133, 0.4)",
    "aupeazdm": "rgba(0, 0, 0, 0.3)",
    "jvhmlskx": "rgba(255, 255, 255, 0.1)",
    "yakfpmhl": "rgba(255, 255, 255, 0.15)",
    "wboyroyc": "rgba(17, 18, 19, 0.5)",
    "dateLabelBg": "rgba(255, 255, 255, 0.08)",
    "vocsgcxy": "rgba(0, 0, 0, 0.5)",
    "mkykhqkw": "#d0d8de",
    "tyvedwbe": "rgba(0, 0, 0, 0.5)"
  },
  "id": "hatsune-miku-misskey-v12"
}
